cgshop2021_pyutils/__init__.py
cgshop2021_pyutils/instance/__init__.py
cgshop2021_pyutils/instance/instance.py
cgshop2021_pyutils/instance/instance_base_database.py
cgshop2021_pyutils/instance/instance_database.py
cgshop2021_pyutils/instance/instance_file_database.py
cgshop2021_pyutils/instance/instance_reader.py
cgshop2021_pyutils/instance/instance_writer.py
cgshop2021_pyutils/instance/instance_zip_database.py
cgshop2021_pyutils/solution/__init__.py
cgshop2021_pyutils/solution/direction.py
cgshop2021_pyutils/solution/errors.py
cgshop2021_pyutils/solution/solution.py
cgshop2021_pyutils/solution/solution_reader.py
cgshop2021_pyutils/solution/solution_step.py
cgshop2021_pyutils/solution/solution_validator.py
cgshop2021_pyutils/solution/solution_writer.py
cgshop2021_pyutils/solution/zip_reader.py
cgshop2021_pyutils/solution/zip_reader_errors.py
cgshop2021_pyutils/solution/zip_writer.py
cgshop2021_pyutils/visualization/__init__.py
cgshop2021_pyutils/visualization/interactive.py
cgshop2021_pyutils-0.1.1.dist-info/METADATA
cgshop2021_pyutils-0.1.1.dist-info/WHEEL
cgshop2021_pyutils-0.1.1.dist-info/top_level.txt
cgshop2021_pyutils-0.1.1.dist-info/RECORD
