Metadata-Version: 2.1
Name: cgshop2021-pyutils
Version: 0.1.1
Summary: Utilities for the CG:SHOP 2021 Optimization Competition on Coordinated Motion Planning.
Home-page: https://cgshop.ibr.cs.tu-bs.de/competition/cg-shop-2021/
Author: TU Braunschweig, IBR, Algorithms Group (Phillip Keldenich and Dominik Krupke)
Author-email: keldenich@ibr.cs.tu-bs.de, krupke@ibr.cs.tu-bs.de
License: UNKNOWN
Platform: UNKNOWN
Classifier: Programming Language :: Python :: 3
Classifier: License :: OSI Approved :: MIT License
Classifier: Development Status :: 5 - Production/Stable
Requires-Python: >=3.6
Requires-Dist: matplotlib
Requires-Dist: chardet
